mmf_serve/__init__.py
mmf_serve/__main__.py
mmf_serve/config.py
mmf_serve/fastapi_tasks.py
mmf_serve/fastapi_wrapper.py
mmf_serve/logger.py
mmf_serve/patch_upload_file.py
mmf_serve/rabbit_wrapper.py
mmf_serve/token_pb2.py
mmf_serve/token_proto.c
mmf_serve/token_proto.pxd
mmf_serve/token_proto.pyx
mmf_serve/verify.py
mmf_serve-0.1.9.dist-info/entry_points.txt
mmf_serve-0.1.9.dist-info/WHEEL
mmf_serve-0.1.9.dist-info/METADATA
mmf_serve-0.1.9.dist-info/RECORD
